setup.py
aioffsend/__init__.py
aioffsend/highlevel.py
aioffsend/lowlevel.py
aioffsend/midlevel.py
aioffsend/utillies.py
aioffsend.egg-info/PKG-INFO
aioffsend.egg-info/SOURCES.txt
aioffsend.egg-info/dependency_links.txt
aioffsend.egg-info/requires.txt
aioffsend.egg-info/top_level.txt